TechSolve_manim/__init__.py
TechSolve_manim/main.py
techsolve_manim-0.0.1.dist-info/METADATA
techsolve_manim-0.0.1.dist-info/WHEEL
techsolve_manim-0.0.1.dist-info/licenses/LICENSE
techsolve_manim-0.0.1.dist-info/RECORD
